pyastroapi/__init__.py
pyastroapi/articles.py
pyastroapi/libraries.py
pyastroapi/search.py
pyastroapi/api/__init__.py
pyastroapi/api/author.py
pyastroapi/api/citation_helper.py
pyastroapi/api/classic.py
pyastroapi/api/exceptions.py
pyastroapi/api/export.py
pyastroapi/api/http.py
pyastroapi/api/libraries.py
pyastroapi/api/metrics.py
pyastroapi/api/notifications.py
pyastroapi/api/recommender.py
pyastroapi/api/reference.py
pyastroapi/api/resolver.py
pyastroapi/api/search.py
pyastroapi/api/solr.py
pyastroapi/api/stored.py
pyastroapi/api/token.py
pyastroapi/api/urls.py
pyastroapi/api/utils.py
pyastroapi/api/visualization.py
pyastroapi/extras/__init__.py
pyastroapi/extras/bibtex.py
pyastroapi/extras/urls.py
pyastroapi-2.0.4.dist-info/LICENSE
pyastroapi-2.0.4.dist-info/METADATA
pyastroapi-2.0.4.dist-info/WHEEL
pyastroapi-2.0.4.dist-info/top_level.txt
pyastroapi-2.0.4.dist-info/zip-safe
pyastroapi-2.0.4.dist-info/RECORD
