Metadata-Version: 2.1
Name: pyastroapi
Version: 2.0.4
Summary: "Low level library interfacing with NASA's ADSABS api"
Home-page: https://github.com/rjfarmer/pyAstroApi
Author: Robert Farmer
Author-email: robert.j.farmer37@gmail.com
License: BSD 3-Clause License
Platform: unix
Platform: linux
Platform: osx
Platform: cygwin
Platform: win32
Classifier: Programming Language :: Python :: 3
Classifier: Programming Language :: Python :: 3 :: Only
Classifier: Programming Language :: Python :: 3.7
Classifier: Programming Language :: Python :: 3.8
Classifier: Programming Language :: Python :: 3.9
Classifier: Programming Language :: Python :: 3.10
Classifier: Programming Language :: Python :: 3.11
Classifier: Topic :: Scientific/Engineering :: Astronomy
Classifier: Intended Audience :: Science/Research
Requires-Python: >=3.7
License-File: LICENSE
Requires-Dist: requests (>=2)
Provides-Extra: testing
Requires-Dist: pytest (>=6.0) ; extra == 'testing'
Requires-Dist: pytest-cov (>=.0) ; extra == 'testing'
Requires-Dist: mypy (>=0.910) ; extra == 'testing'
Requires-Dist: tox (>=3.24) ; extra == 'testing'
Requires-Dist: pytest-vcr ; extra == 'testing'
Requires-Dist: vcrpy ; extra == 'testing'
